package/__init__.py
package/config_args.py
package/git_works.py
package/parse_works.py
package/vcs_p.py
package/work_args.py
vcs_p_utils-0.0.2.dist-info/METADATA
vcs_p_utils-0.0.2.dist-info/WHEEL
vcs_p_utils-0.0.2.dist-info/entry_points.txt
vcs_p_utils-0.0.2.dist-info/top_level.txt
vcs_p_utils-0.0.2.dist-info/RECORD
